README.md
setup.cfg
setup.py
qss_debugger/__init__.py
qss_debugger/compiler.py
qss_debugger/debugger.py
qss_debugger/explorer.py
qss_debugger/painter.py
qss_debugger.egg-info/PKG-INFO
qss_debugger.egg-info/SOURCES.txt
qss_debugger.egg-info/dependency_links.txt
qss_debugger.egg-info/requires.txt
qss_debugger.egg-info/top_level.txt
venv/Lib/collections/__init__.py
venv/Lib/collections/abc.py
venv/Lib/distutils/__init__.py
venv/Lib/encodings/__init__.py
venv/Lib/encodings/aliases.py
venv/Lib/encodings/ascii.py
venv/Lib/encodings/base64_codec.py
venv/Lib/encodings/big5.py
venv/Lib/encodings/big5hkscs.py
venv/Lib/encodings/bz2_codec.py
venv/Lib/encodings/charmap.py
venv/Lib/encodings/cp037.py
venv/Lib/encodings/cp1006.py
venv/Lib/encodings/cp1026.py
venv/Lib/encodings/cp1125.py
venv/Lib/encodings/cp1140.py
venv/Lib/encodings/cp1250.py
venv/Lib/encodings/cp1251.py
venv/Lib/encodings/cp1252.py
venv/Lib/encodings/cp1253.py
venv/Lib/encodings/cp1254.py
venv/Lib/encodings/cp1255.py
venv/Lib/encodings/cp1256.py
venv/Lib/encodings/cp1257.py
venv/Lib/encodings/cp1258.py
venv/Lib/encodings/cp273.py
venv/Lib/encodings/cp424.py
venv/Lib/encodings/cp437.py
venv/Lib/encodings/cp500.py
venv/Lib/encodings/cp65001.py
venv/Lib/encodings/cp720.py
venv/Lib/encodings/cp737.py
venv/Lib/encodings/cp775.py
venv/Lib/encodings/cp850.py
venv/Lib/encodings/cp852.py
venv/Lib/encodings/cp855.py
venv/Lib/encodings/cp856.py
venv/Lib/encodings/cp857.py
venv/Lib/encodings/cp858.py
venv/Lib/encodings/cp860.py
venv/Lib/encodings/cp861.py
venv/Lib/encodings/cp862.py
venv/Lib/encodings/cp863.py
venv/Lib/encodings/cp864.py
venv/Lib/encodings/cp865.py
venv/Lib/encodings/cp866.py
venv/Lib/encodings/cp869.py
venv/Lib/encodings/cp874.py
venv/Lib/encodings/cp875.py
venv/Lib/encodings/cp932.py
venv/Lib/encodings/cp949.py
venv/Lib/encodings/cp950.py
venv/Lib/encodings/euc_jis_2004.py
venv/Lib/encodings/euc_jisx0213.py
venv/Lib/encodings/euc_jp.py
venv/Lib/encodings/euc_kr.py
venv/Lib/encodings/gb18030.py
venv/Lib/encodings/gb2312.py
venv/Lib/encodings/gbk.py
venv/Lib/encodings/hex_codec.py
venv/Lib/encodings/hp_roman8.py
venv/Lib/encodings/hz.py
venv/Lib/encodings/idna.py
